pgn_clis/__init__.py
pgn_clis/lib/__init__.py
pgn_clis/lib/clean.py
pgn_clis/lib/download.py
pgn_clis/lib/random_samples.py
pgn_clis/lib/sans2fens.py
pgn_clis/lib/sans2ucis.py
pgn_clis/lib/style_sans.py
pgn_clis/scripts/__init__.py
pgn_clis/scripts/clean.py
pgn_clis/scripts/download.py
pgn_clis/scripts/random_samples.py
pgn_clis/scripts/sans2fens.py
pgn_clis/scripts/sans2ucis.py
pgn_clis/scripts/style_sans.py
pgn_clis-0.1.22.dist-info/METADATA
pgn_clis-0.1.22.dist-info/WHEEL
pgn_clis-0.1.22.dist-info/entry_points.txt
pgn_clis-0.1.22.dist-info/top_level.txt
pgn_clis-0.1.22.dist-info/RECORD
