Metadata-Version: 2.1
Name: pgn-clis
Version: 0.1.22
Summary: package_description
Author-email: Marcel Claramunt <marcel@moveread.com>
Project-URL: repo, https://github.com/moveread/chess.git
Requires-Python: >=3.10
Requires-Dist: chess-utils
Requires-Dist: chess-notation
Requires-Dist: fs-tools
